Verilog/LabFinal/mux2.v
module mux2(input [3:0] d0, d1,
            input s,
            output [3:0] y);

	assign y = s ? d1 : d0;

endmodule

Verilog/LabFinal/mux4.v
module mux4(input [3:0] d0, d1, d2, d3,
            input [1:0] s,
            output [3:0] y);
  
  wire [3:0] lowmux_out, highmux_out;
  
  mux2 lowmux(.d0(d0), .d1(d1), .s(s[0]), .y(lowmux_out));
  mux2 highmux(.d0(d2), .d1(d3), .s(s[0]), .y(highmux_out));
  mux2 finalmux(.d0(lowmux_out), .d1(highmux_out), .s(s[1]), .y(y));
  
endmodule

Verilog/LabFinal/mux4_tb.v
module mux4_tb;
  reg[3:0] in0, in1, in2, in3;
  wire[3:0] out;
  reg[1:0] s;
  
  initial begin
    $dumpfile("mux4_tb.vcd");
    $dumpvars(0, mux4_tb);
    
    #1
    s = 0;
    in0 = 2;
    in1 = 4;
    in2 = 6;
    in3 = 9;
    
    #1
    s = 1;
    
    #1
    s = 2;

    #1
    s = 3;
    
    #1
    s = 0;
    
    #1
    s = 1;
    
    #1
    s = 2;

    #1
    s = 3;

    #2
    $finish;
    
  end
  
  mux4 mymux4(.y(out), .d0(in0), .d1(in1), .d2(in2), .d3(in3), .s(s));
  
  initial begin
    $monitor("in0 = %d : in1 = %d : in2 = %d : in3 = %d : s = %d : out = %d", in0, in1, in2, in3, s, out);
  end

endmodule

Verilog/LabFinal/mux4_tb.vcd
$date
	Wed Nov 02 00:26:43 2022
$end
$version
	Icarus Verilog
$end
$timescale
	1s
$end
$scope module mux4_tb $end
$var wire 4 ! out [3:0] $end
$var reg 4 " in0 [3:0] $end
$var reg 4 # in1 [3:0] $end
$var reg 4 $ in2 [3:0] $end
$var reg 4 % in3 [3:0] $end
$var reg 2 & s [1:0] $end
$scope module mymux4 $end
$var wire 4 ' d0 [3:0] $end
$var wire 4 ( d1 [3:0] $end
$var wire 4 ) d2 [3:0] $end
$var wire 4 * d3 [3:0] $end
$var wire 2 + s [1:0] $end
$var wire 4 , y [3:0] $end
$var wire 4 - lowmux_out [3:0] $end
$var wire 4 . highmux_out [3:0] $end
$scope module finalmux $end
$var wire 1 / s $end
$var wire 4 0 y [3:0] $end
$var wire 4 1 d1 [3:0] $end
$var wire 4 2 d0 [3:0] $end
$upscope $end
$scope module highmux $end
$var wire 4 3 d0 [3:0] $end
$var wire 4 4 d1 [3:0] $end
$var wire 1 5 s $end
$var wire 4 6 y [3:0] $end
$upscope $end
$scope module lowmux $end
$var wire 4 7 d0 [3:0] $end
$var wire 4 8 d1 [3:0] $end
$var wire 1 9 s $end
$var wire 4 : y [3:0] $end
$upscope $end
$upscope $end
$upscope $end
$enddefinitions $end
$comment Show the parameter values. $end
$dumpall
$end
#0
$dumpvars
bx :
x9
bx 8
bx 7
bx 6
x5
bx 4
bx 3
bx 2
bx 1
bx 0
x/
bx .
bx -
bx ,
bx +
bx *
bx )
bx (
bx '
bx &
bx %
bx $
bx #
bx "
bx !
$end
#1
b10 !
b10 ,
b10 0
b110 .
b110 1
b110 6
b10 -
b10 2
b10 :
09
05
0/
b1001 %
b1001 *
b1001 4
b110 $
b110 )
b110 3
b100 #
b100 (
b100 8
b10 "
b10 '
b10 7
b0 &
b0 +
#2
b100 !
b100 ,
b100 0
b100 -
b100 2
b100 :
b1001 .
b1001 1
b1001 6
19
15
b1 &
b1 +
#3
b10 -
b10 2
b10 :
b110 .
b110 1
b110 6
b110 !
b110 ,
b110 0
09
05
1/
b10 &
b10 +
#4
b1001 !
b1001 ,
b1001 0
b100 -
b100 2
b100 :
b1001 .
b1001 1
b1001 6
19
15
b11 &
b11 +
#5
b10 -
b10 2
b10 :
b110 .
b110 1
b110 6
b10 !
b10 ,
b10 0
09
05
0/
b0 &
b0 +
#6
b100 !
b100 ,
b100 0
b100 -
b100 2
b100 :
b1001 .
b1001 1
b1001 6
19
15
b1 &
b1 +
#7
b10 -
b10 2
b10 :
b110 .
b110 1
b110 6
b110 !
b110 ,
b110 0
09
05
1/
b10 &
b10 +
#8
b1001 !
b1001 ,
b1001 0
b100 -
b100 2
b100 :
b1001 .
b1001 1
b1001 6
19
15
b11 &
b11 +
